{
	"cmake" : 
	{
		"generator" : 
		{
			"multiConfig" : false,
			"name" : "MinGW Makefiles"
		},
		"paths" : 
		{
			"cmake" : "D:/program/cmake/bin/cmake.exe",
			"cpack" : "D:/program/cmake/bin/cpack.exe",
			"ctest" : "D:/program/cmake/bin/ctest.exe",
			"root" : "D:/program/cmake/share/cmake-3.25"
		},
		"version" : 
		{
			"isDirty" : false,
			"major" : 3,
			"minor" : 25,
			"patch" : 1,
			"string" : "3.25.1",
			"suffix" : ""
		}
	},
	"objects" : 
	[
		{
			"jsonFile" : "codemodel-v2-0e90ee595d51e50fa8d8.json",
			"kind" : "codemodel",
			"version" : 
			{
				"major" : 2,
				"minor" : 4
			}
		},
		{
			"jsonFile" : "cache-v2-61cbdf4d16b6c61a8df9.json",
			"kind" : "cache",
			"version" : 
			{
				"major" : 2,
				"minor" : 0
			}
		},
		{
			"jsonFile" : "cmakeFiles-v1-9f25b7f1c44798c1cb7d.json",
			"kind" : "cmakeFiles",
			"version" : 
			{
				"major" : 1,
				"minor" : 0
			}
		},
		{
			"jsonFile" : "toolchains-v1-17e62996e4a370548d83.json",
			"kind" : "toolchains",
			"version" : 
			{
				"major" : 1,
				"minor" : 0
			}
		}
	],
	"reply" : 
	{
		"client-vscode" : 
		{
			"query.json" : 
			{
				"requests" : 
				[
					{
						"kind" : "cache",
						"version" : 2
					},
					{
						"kind" : "codemodel",
						"version" : 2
					},
					{
						"kind" : "toolchains",
						"version" : 1
					},
					{
						"kind" : "cmakeFiles",
						"version" : 1
					}
				],
				"responses" : 
				[
					{
						"jsonFile" : "cache-v2-61cbdf4d16b6c61a8df9.json",
						"kind" : "cache",
						"version" : 
						{
							"major" : 2,
							"minor" : 0
						}
					},
					{
						"jsonFile" : "codemodel-v2-0e90ee595d51e50fa8d8.json",
						"kind" : "codemodel",
						"version" : 
						{
							"major" : 2,
							"minor" : 4
						}
					},
					{
						"jsonFile" : "toolchains-v1-17e62996e4a370548d83.json",
						"kind" : "toolchains",
						"version" : 
						{
							"major" : 1,
							"minor" : 0
						}
					},
					{
						"jsonFile" : "cmakeFiles-v1-9f25b7f1c44798c1cb7d.json",
						"kind" : "cmakeFiles",
						"version" : 
						{
							"major" : 1,
							"minor" : 0
						}
					}
				]
			}
		}
	}
}
